Metadata-Version: 2.1
Name: odoo14-addon-account_statement_import_base
Version: 14.0.1.0.1.dev13
Summary: Base module for Bank Statement Import
Home-page: https://github.com/OCA/bank-statement-import
Author: Akretion, Odoo Community Association (OCA)
Author-email: support@odoo-community.org
License: LGPL-3
Classifier: Programming Language :: Python
Classifier: Framework :: Odoo
Classifier: Framework :: Odoo :: 14.0
Classifier: License :: OSI Approved :: GNU Lesser General Public License v3 (LGPLv3)
Classifier: Development Status :: 6 - Mature
Requires-Python: >=3.6
Requires-Dist: odoo<14.1dev,>=14.0a
